pipomatic_pipomatic_obfuscate_files.py
pipomatic_pipomatic_obfuscate_files-0.2.dist-info/WHEEL
pipomatic_pipomatic_obfuscate_files-0.2.dist-info/METADATA
pipomatic_pipomatic_obfuscate_files-0.2.dist-info/RECORD
