Metadata-Version: 2.1
Name: pipomatic_pipomatic_obfuscate_files
Version: 0.2
Summary: Obfuscate files package
Home-page: http://www.mybusinessautomated.com
License: UNKNOWN
Author: Hudge
Author-email: doug@mybusinessautomated.com
Classifier: License :: OSI Approved :: MIT License
